idascript/__init__.py
idascript/__main__.py
idascript/ida.py
idascript/nop_script.py
idascript/py.typed
idascript/utils.py
idascript-0.4.1.dist-info/licenses/LICENSE
idascript-0.4.1.dist-info/METADATA
idascript-0.4.1.dist-info/WHEEL
idascript-0.4.1.dist-info/entry_points.txt
idascript-0.4.1.dist-info/top_level.txt
idascript-0.4.1.dist-info/RECORD
