Metadata-Version: 2.4
Name: idascript
Version: 0.4.1
Summary: IDA Pro wrapper to launch script on binaries
Author-email: Robin David <rdavid@quarkslab.com>
License: Apache Software License (Apache License, Version 2)
Project-URL: Homepage, https://github.com/quarkslab/idascript
Project-URL: Repository, https://github.com/quarkslab/idascript
Project-URL: Documentation, https://quarkslab.github.io/diffing-portal/idascript/README.html
Project-URL: Bug Tracker, https://github.com/quarkslab/idascript/issues
Classifier: Topic :: Security
Classifier: Environment :: Console
Classifier: Operating System :: OS Independent
Requires-Python: >=3.8
License-File: LICENSE
Requires-Dist: python-magic; os_name != "nt"
Requires-Dist: python-magic-bin; os_name == "nt"
Requires-Dist: click
Requires-Dist: progressbar2
Requires-Dist: psutil
Dynamic: license-file
